[
	{
		"id": "A1",
		"name": "Economic",
		"weight": 1,
		"weights": [10,15,20,10,20,15,10],
		"left": {
			"name": "Intervention",
			"color": "#000000",
			"icon": "value_images/value.svg",
			"description": ""
		},
		"right": {
			"name": "Laissez-faire",
			"color": "#000000",
			"icon": "value_images/value.svg",
			"description": ""
		},
		"tiers": [
			"Communist",
			"Socialist",
			"Collective",
			"Syncretic",
			"Individual",
			"Private",
			"Propertarian"
		]
	},
	{
		"id": "A2",
		"name": "Focus",
		"weight": 0.95,
		"weights": [10,15,20,10,20,15,10],
		"left": {
			"name": "Populism",
			"color": "#000000",
			"icon": "value_images/value.svg",
			"description": ""
		},
		"right": {
			"name": "Elitism",
			"color": "#000000",
			"icon": "value_images/value.svg",
			"description": ""
		},
		"tiers": [
			"Planned",
			"Directed",
			"Regulated",
			"Intervening",
			"Permissive",
			"Free Market",
			"Laissez-Faire"
		]
	},
	{
		"id": "A3",
		"name": "Government",
		"weight": 1,
		"weights": [10,15,20,10,20,15,10],
		"left": {
			"name": "Statism",
			"color": "#000000",
			"icon": "value_images/value.svg",
			"description": ""
		},
		"right": {
			"name": "Totalitarianism",
			"color": "#000000",
			"icon": "value_images/value.svg",
			"description": ""
		},
		"tiers": [
			"Autocratic",
			"Concentrated",
			"Unified",
			"Representative",
			"Dispersed",
			"Decentral",
			"Anarchist"
		]
	},
	{
		"id": "A4",
		"name": "Identity",
		"weight": 0.5,
		"weights": [10,15,20,10,20,15,10],
		"left": {
			"name": "Inclusivity",
			"color": "#000000",
			"icon": "value_images/value.svg",
			"description": ""
		},
		"right": {
			"name": "Supremacy",
			"color": "#000000",
			"icon": "value_images/value.svg",
			"description": ""
		},
		"tiers": [
			"Intersectional",
			"Inclusive",
			"Respectful",
			"Normative",
			"Prejudicial",
			"Discriminatory",
			"Supremacist"
		]
	},
	{
		"id": "A5",
		"name": "Army",
		"weight": 0.6,
		"weights": [10,15,20,10,20,15,10],
		"left": {
			"name": "Military",
			"color": "#000000",
			"icon": "value_images/value.svg",
			"description": ""
		},
		"right": {
			"name": "Peace",
			"color": "#000000",
			"icon": "value_images/value.svg",
			"description": ""
		},
		"tiers": [
			"Intersectional",
			"Inclusive",
			"Respectful",
			"Normative",
			"Prejudicial",
			"Discriminatory",
			"Supremacist"
		]
	},
	{
		"id": "A6",
		"name": "Technology",
		"weight": 0.6,
		"weights": [10,15,20,10,20,15,10],
		"left": {
			"name": "Antique",
			"color": "#000000",
			"icon": "value_images/value.svg",
			"description": ""
		},
		"right": {
			"name": "Accelerated",
			"color": "#000000",
			"icon": "value_images/value.svg",
			"description": ""
		},
		"tiers": [
			"Antiquated",
			"Traditional",
			"Conservative",
			"Conventional",
			"Neoteric",
			"Progressive",
			"Futuristic"
		]
	},
	{
		"id": "A7",
		"name": "Religion",
		"weight": 0.6,
		"weights": [10,15,20,10,20,15,10],
		"left": {
			"name": "Anti-Theist",
			"color": "#000000",
			"icon": "value_images/value.svg",
			"description": ""
		},
		"right": {
			"name": "Fanatical Theist",
			"color": "#000000",
			"icon": "value_images/value.svg",
			"description": ""
		},
		"tiers": [
			"Antiquated",
			"Traditional",
			"Conservative",
			"Conventional",
			"Neoteric",
			"Progressive",
			"Futuristic"
		]
	}
]
